tree_2_file/__init__.py
tree_2_file/cli.py
tree_2_file/main.py
tree_2_file/tree_2_file.py
tree_2_file-0.1.0.dist-info/AUTHORS.rst
tree_2_file-0.1.0.dist-info/LICENSE
tree_2_file-0.1.0.dist-info/METADATA
tree_2_file-0.1.0.dist-info/WHEEL
tree_2_file-0.1.0.dist-info/top_level.txt
tree_2_file-0.1.0.dist-info/RECORD
