Metadata-Version: 2.1
Name: tree_2_file
Version: 0.1.0
Summary: Take text representing a directory tree and create the directories and files on the actual filesystem
Author-email: Reed Jones <reedmjones@outlook.com>
Maintainer-email: Reed Jones <reedmjones@outlook.com>
License: MIT license
Project-URL: bugs, https://github.com/reedjones/tree_2_file/issues
Project-URL: changelog, https://github.com/reedjones/tree_2_file/blob/master/changelog.md
Project-URL: homepage, https://github.com/reedjones/tree_2_file
Classifier: Development Status :: 5 - Production/Stable
Classifier: Operating System :: OS Independent
Classifier: Intended Audience :: Developers
Classifier: License :: OSI Approved :: MIT License
Classifier: Programming Language :: Python :: 3.11
Classifier: Topic :: Education :: Testing
License-File: LICENSE
License-File: AUTHORS.rst
Requires-Dist: pyperclip>=1.0.0
Provides-Extra: dev
Requires-Dist: coverage; extra == "dev"
Requires-Dist: mypy; extra == "dev"
Requires-Dist: pytest; extra == "dev"
Requires-Dist: ruff; extra == "dev"
